jbatch/__init__.py
jbatch/__main__.py
jbatch/err
jbatch/out
jbatch/sa
jbatch/sc
jbatch/scripts.py
jbatch/sq
jbatch-0.2.4.dist-info/METADATA
jbatch-0.2.4.dist-info/WHEEL
jbatch-0.2.4.dist-info/entry_points.txt
jbatch-0.2.4.dist-info/RECORD
