Metadata-Version: 2.1
Name: jbatch
Version: 0.2.4
Summary: Simple tool to wrap and execute sbatch commands from Jupyter Notebook cells with Conda envs
License: MIT
Author: Dmitry Solovey
Author-email: dsolovey@ist.ac.at
Requires-Python: >=3.12,<4.0
Classifier: License :: OSI Approved :: MIT License
Classifier: Programming Language :: Python :: 3
Classifier: Programming Language :: Python :: 3.12
